package_demo/__init__.py
package_demo/my_file.py
package_demo/my_other_file.py
package_demo/state_info.py
package_demo/my_folder/__init__.py
package_demo/my_folder/cities.json
package_demo/my_folder/my_nested_file.py
packaging_demo_sheiphan-0.0.2.dist-info/METADATA
packaging_demo_sheiphan-0.0.2.dist-info/WHEEL
packaging_demo_sheiphan-0.0.2.dist-info/top_level.txt
packaging_demo_sheiphan-0.0.2.dist-info/RECORD
