Metadata-Version: 2.1
Name: packaging_demo_sheiphan
Version: 0.0.2
Summary: My package description
Author-email: Sheiphan Joseph <sheiphanshaijan@gmail.com>
License: MIT
Keywords: one,two
Classifier: Programming Language :: Python :: 3
Requires-Python: >=3.8
Requires-Dist: fastapi
Requires-Dist: requests
Requires-Dist: importlib-metadata ; python_version < "3.10"
Provides-Extra: colors
Requires-Dist: rich ; extra == 'colors'
Provides-Extra: dev
Requires-Dist: packaging-demo[release,static-code-qa,test] ; extra == 'dev'
Provides-Extra: release
Requires-Dist: build ; extra == 'release'
Requires-Dist: twine ; extra == 'release'
Provides-Extra: static-code-qa
Requires-Dist: pre-commit ; extra == 'static-code-qa'
Provides-Extra: test
Requires-Dist: pytest ; extra == 'test'
Requires-Dist: pytest-cov ; extra == 'test'
